vmod/__init__.py
vmod/inverse.py
vmod/util.py
vmod/data/__init__.py
vmod/data/data.py
vmod/data/edm.py
vmod/data/gnss.py
vmod/data/insar.py
vmod/data/joint.py
vmod/data/level.py
vmod/data/tilt.py
vmod/source/__init__.py
vmod/source/cdm.py
vmod/source/crfault.py
vmod/source/mctigue.py
vmod/source/mogi.py
vmod/source/nish.py
vmod/source/okada.py
vmod/source/penny.py
vmod/source/regdis.py
vmod/source/rfault.py
vmod/source/source.py
vmod/source/vshell.py
vmod/source/vsphere.py
vmod/source/wellsite.py
vmod/source/yang.py
vmod_geodesy-2.0.0.dist-info/licenses/LICENSE
vmod_geodesy-2.0.0.dist-info/METADATA
vmod_geodesy-2.0.0.dist-info/WHEEL
vmod_geodesy-2.0.0.dist-info/top_level.txt
vmod_geodesy-2.0.0.dist-info/RECORD
