Metadata-Version: 2.4
Name: vmod-geodesy
Version: 2.0.0
Summary: Versatile Modeling of Deformation
Author-email: Mario Angarita Vargas <mfangaritasr@alaska.edu>, Ronni Grapenthin <rgrapenthin@alaska.edu>, Scott Henderson <scottyh@uw.edu>, Michael Christoffersen <mchristoffersen@alaska.edu>, Kyle Anderson <kranderson@usgs.gov>
License: MIT License
Project-URL: documentation, https://github.com/uafgeotools/vmod
Project-URL: repository, https://github.com/uafgeotools/vmod
Requires-Python: >=3.8
License-File: LICENSE
Requires-Dist: h5py==3.*
Requires-Dist: matplotlib==3.*
Requires-Dist: numpy==2.*
Requires-Dist: pandas==2.*
Requires-Dist: rasterio==1.*
Requires-Dist: scipy==1.*
Requires-Dist: scikit-image==0.*
Requires-Dist: utm==0.7.0
Requires-Dist: jupyterlab==4.*
Requires-Dist: corner==2.*
Requires-Dist: emcee==3.*
Requires-Dist: tqdm
Requires-Dist: ipympl
Requires-Dist: pygmt
Requires-Dist: hankel
Dynamic: license-file
